prompt_foundry_python_sdk/__init__.py
prompt_foundry_python_sdk/_base_client.py
prompt_foundry_python_sdk/_client.py
prompt_foundry_python_sdk/_compat.py
prompt_foundry_python_sdk/_constants.py
prompt_foundry_python_sdk/_exceptions.py
prompt_foundry_python_sdk/_files.py
prompt_foundry_python_sdk/_models.py
prompt_foundry_python_sdk/_qs.py
prompt_foundry_python_sdk/_resource.py
prompt_foundry_python_sdk/_response.py
prompt_foundry_python_sdk/_streaming.py
prompt_foundry_python_sdk/_types.py
prompt_foundry_python_sdk/_version.py
prompt_foundry_python_sdk/py.typed
prompt_foundry_python_sdk/_utils/__init__.py
prompt_foundry_python_sdk/_utils/_logs.py
prompt_foundry_python_sdk/_utils/_proxy.py
prompt_foundry_python_sdk/_utils/_reflection.py
prompt_foundry_python_sdk/_utils/_streams.py
prompt_foundry_python_sdk/_utils/_sync.py
prompt_foundry_python_sdk/_utils/_transform.py
prompt_foundry_python_sdk/_utils/_typing.py
prompt_foundry_python_sdk/_utils/_utils.py
prompt_foundry_python_sdk/lib/.keep
prompt_foundry_python_sdk/resources/__init__.py
prompt_foundry_python_sdk/resources/completion.py
prompt_foundry_python_sdk/resources/evaluation_assertions.py
prompt_foundry_python_sdk/resources/evaluations.py
prompt_foundry_python_sdk/resources/prompts.py
prompt_foundry_python_sdk/resources/tools.py
prompt_foundry_python_sdk/types/__init__.py
prompt_foundry_python_sdk/types/completion_create_params.py
prompt_foundry_python_sdk/types/completion_create_response.py
prompt_foundry_python_sdk/types/evaluation.py
prompt_foundry_python_sdk/types/evaluation_assertion.py
prompt_foundry_python_sdk/types/evaluation_assertion_create_params.py
prompt_foundry_python_sdk/types/evaluation_assertion_delete_response.py
prompt_foundry_python_sdk/types/evaluation_assertion_list_params.py
prompt_foundry_python_sdk/types/evaluation_assertion_list_response.py
prompt_foundry_python_sdk/types/evaluation_assertion_update_params.py
prompt_foundry_python_sdk/types/evaluation_create_params.py
prompt_foundry_python_sdk-0.1.0a13.dist-info/METADATA
prompt_foundry_python_sdk-0.1.0a13.dist-info/WHEEL
prompt_foundry_python_sdk-0.1.0a13.dist-info/licenses/LICENSE
prompt_foundry_python_sdk-0.1.0a13.dist-info/RECORD
