Metadata-Version: 2.3
Name: prompt_foundry_python_sdk
Version: 0.1.0a13
Summary: The prompt engineering, prompt management, and prompt evaluation tool for Python 
Project-URL: Homepage, https://https://www.promptfoundry.ai
Project-URL: Repository, https://github.com/prompt-foundry/python-sdk
Project-URL: Documentation, https://docs.promptfoundry.ai/libraries/python
Author-email: Prompt Foundry <dev-feedback@promptfoundry.ai>
License-Expression: Apache-2.0
License-File: LICENSE
Keywords: llm evaluation,prompt engineering,prompt management,prompt testing
Classifier: Intended Audience :: Developers
Classifier: License :: OSI Approved :: Apache Software License
Classifier: Operating System :: MacOS
Classifier: Operating System :: Microsoft :: Windows
Classifier: Operating System :: OS Independent
Classifier: Operating System :: POSIX
Classifier: Operating System :: POSIX :: Linux
Classifier: Programming Language :: Python :: 3.7
Classifier: Programming Language :: Python :: 3.8
Classifier: Programming Language :: Python :: 3.9
Classifier: Programming Language :: Python :: 3.10
Classifier: Programming Language :: Python :: 3.11
Classifier: Programming Language :: Python :: 3.12
Classifier: Topic :: Software Development :: Libraries :: Python Modules
Classifier: Typing :: Typed
Requires-Python: >=3.7
Requires-Dist: anyio<5,>=3.5.0
Requires-Dist: cached-property; python_version < '3.8'
Requires-Dist: distro<2,>=1.7.0
Requires-Dist: httpx<1,>=0.23.0
Requires-Dist: pydantic<3,>=1.9.0
Requires-Dist: sniffio
Requires-Dist: typing-extensions<5,>=4.7
